reyna/__init__.py
reyna/DGFEM/two_dimensional/main.py
reyna/DGFEM/two_dimensional/plotter.py
reyna/DGFEM/two_dimensional/_auxilliaries/assembly_aux.py
reyna/DGFEM/two_dimensional/_auxilliaries/boundary_information.py
reyna/DGFEM/two_dimensional/_auxilliaries/polygonal_basis_utils.py
reyna/DGFEM/two_dimensional/_auxilliaries/assembly/boundary_assembly.py
reyna/DGFEM/two_dimensional/_auxilliaries/assembly/full_assembly.py
reyna/DGFEM/two_dimensional/_auxilliaries/error_assembly/boundary_assembly.py
reyna/DGFEM/two_dimensional/_auxilliaries/error_assembly/full_assembly.py
reyna/geometry/two_dimensional/DGFEM.py
reyna/polymesher/two_dimensional/domains.py
reyna/polymesher/two_dimensional/main.py
reyna/polymesher/two_dimensional/visualisation.py
reyna/polymesher/two_dimensional/_auxilliaries/abstraction.py
reyna/polymesher/two_dimensional/_auxilliaries/distance_functions.py
reyna-1.3.0.dist-info/licenses/LICENSE.txt
reyna-1.3.0.dist-info/METADATA
reyna-1.3.0.dist-info/WHEEL
reyna-1.3.0.dist-info/top_level.txt
reyna-1.3.0.dist-info/RECORD
