Metadata-Version: 2.4
Name: reyna
Version: 1.3.0
Summary: A minimal overhead, vectorised, polygonal discontinuous Galerkin finite element library.
Author-email: mattevs24 <matt.evans2411@gmail.com>
License: MIT License
Keywords: discontinuous,Galerkin,finite,element,numerics,methods,numerical analysis,dicontinuous Galerkin,dG,finite element methods,NA,pdes,partial,differential,equations,partial differential equations,linear algebra,LA,sparse,matrices
Classifier: Development Status :: 4 - Beta
Classifier: Programming Language :: Python :: 3.8
Classifier: Topic :: Scientific/Engineering
Classifier: Topic :: Scientific/Engineering :: Mathematics
Classifier: Topic :: Scientific/Engineering :: Physics
Classifier: Topic :: Scientific/Engineering :: Visualization
Classifier: Topic :: Software Development :: Libraries :: Python Modules
Classifier: Intended Audience :: Education
Classifier: Intended Audience :: Science/Research
Classifier: Intended Audience :: Developers
Requires-Python: >=3.8
License-File: LICENSE.txt
Requires-Dist: numpy>=1.22.0
Requires-Dist: scipy>=1.4.0
Requires-Dist: shapely>=2.0.0
Requires-Dist: matplotlib>=3.4.0
Requires-Dist: numba==0.58.1
Dynamic: license-file
